ezil/__init__.py
ezil/ezil.py
ezil-0.0.4.dist-info/LICENCE
ezil-0.0.4.dist-info/METADATA
ezil-0.0.4.dist-info/WHEEL
ezil-0.0.4.dist-info/top_level.txt
ezil-0.0.4.dist-info/RECORD
