Metadata-Version: 2.1
Name: ezil
Version: 0.0.4
Summary: Ezil.me mining pool API wrapper
Home-page: https://github.com/derki-source/py-ezil
Author: Marek Derer
Author-email: marek.derer@gmail.com
License: UNKNOWN
Project-URL: Bug Tracker, https://github.com/derki-source/py-ezil/issues
Platform: UNKNOWN
Classifier: Programming Language :: Python :: 3
Classifier: License :: OSI Approved :: MIT License
Classifier: Operating System :: OS Independent
Requires-Python: >=3.6
License-File: LICENCE
